flexmeasures/Readme.md
flexmeasures/__init__.py
flexmeasures/app.py
flexmeasures/conftest.py
flexmeasures/api/Readme.md
flexmeasures/api/__init__.py
flexmeasures/api/conftest.py
flexmeasures/api/common/__init__.py
flexmeasures/api/common/implementations.py
flexmeasures/api/common/responses.py
flexmeasures/api/common/routes.py
flexmeasures/api/common/schemas/__init__.py
flexmeasures/api/common/schemas/assets.py
flexmeasures/api/common/schemas/generic_assets.py
flexmeasures/api/common/schemas/generic_schemas.py
flexmeasures/api/common/schemas/search.py
flexmeasures/api/common/schemas/sensor_data.py
flexmeasures/api/common/schemas/sensors.py
flexmeasures/api/common/schemas/users.py
flexmeasures/api/common/schemas/utils.py
flexmeasures/api/common/schemas/tests/__init__.py
flexmeasures/api/common/schemas/tests/test_sensor_data_schema.py
flexmeasures/api/common/schemas/tests/test_sensors.py
flexmeasures/api/common/utils/__init__.py
flexmeasures/api/common/utils/api_utils.py
flexmeasures/api/common/utils/args_parsing.py
flexmeasures/api/common/utils/deprecation_utils.py
flexmeasures/api/common/utils/validators.py
flexmeasures/api/dev/__init__.py
flexmeasures/api/dev/sensors.py
flexmeasures/api/dev/tests/__init__.py
flexmeasures/api/dev/tests/conftest.py
flexmeasures/api/scripts/generate_open_api_specs.py
flexmeasures/api/sunset/__init__.py
flexmeasures/api/sunset/routes.py
flexmeasures/api/sunset/tests/__init__.py
flexmeasures/api/sunset/tests/test_sunset.py
flexmeasures/api/tests/conftest.py
flexmeasures/api/tests/test_auth_token.py
flexmeasures/api/tests/test_ping.py
flexmeasures/api/tests/test_task_runs.py
flexmeasures/api/tests/utils.py
flexmeasures/api/v3_0/__init__.py
flexmeasures/api/v3_0/accounts.py
flexmeasures/api/v3_0/assets.py
flexmeasures/api/v3_0/deprecated.py
flexmeasures/api/v3_0/health.py
flexmeasures/api/v3_0/public.py
flexmeasures/api/v3_0/sensors.py
flexmeasures/api/v3_0/users.py
flexmeasures/api/v3_0/tests/__init__.py
flexmeasures-0.29.1.dist-info/licenses/LICENSE
flexmeasures-0.29.1.dist-info/METADATA
flexmeasures-0.29.1.dist-info/WHEEL
flexmeasures-0.29.1.dist-info/entry_points.txt
flexmeasures-0.29.1.dist-info/top_level.txt
flexmeasures-0.29.1.dist-info/RECORD
