Metadata-Version: 2.4
Name: flexmeasures
Version: 0.29.1
Summary: The *FlexMeasures Platform* is the intelligent backend to support real-time energy flexibility apps, rapidly and scalable.
Author-email: Seita BV <nicolas@seita.nl>
License-Expression: Apache-2.0
Project-URL: Homepage, https://flexmeasures.io
Project-URL: Documentation, https://flexmeasures.readthedocs.io/
Project-URL: Source code, https://github.com/FlexMeasures/flexmeasures
Keywords: smart grid,renewables,balancing,forecasting,scheduling
Classifier: Environment :: Console
Classifier: Environment :: Web Environment
Classifier: Programming Language :: Python
Classifier: Programming Language :: Python :: 3
Classifier: Programming Language :: Python :: 3.9
Classifier: Programming Language :: Python :: 3.10
Classifier: Programming Language :: Python :: 3.11
Classifier: Programming Language :: Python :: 3.12
Classifier: Framework :: Flask
Classifier: Development Status :: 5 - Production/Stable
Classifier: Operating System :: POSIX :: Linux
Classifier: Operating System :: MacOS :: MacOS X
Classifier: Natural Language :: English
Requires-Python: >=3.9
License-File: LICENSE
Requires-Dist: pyyaml
Requires-Dist: altair
Requires-Dist: pandas
Requires-Dist: pint>=0.19.1
Requires-Dist: py-moneyed
Requires-Dist: iso8601
Requires-Dist: xlrd
Requires-Dist: workalendar
Requires-Dist: inflection
Requires-Dist: inflect
Requires-Dist: pydantic
Requires-Dist: humanize
Requires-Dist: psycopg2-binary
Requires-Dist: bcrypt<=4.0.1
Requires-Dist: argon2_cffi
Requires-Dist: pytz
Requires-Dist: isodate
Requires-Dist: click<8.2.0
Requires-Dist: click-default-group
Requires-Dist: email_validator
Requires-Dist: rq
Requires-Dist: rq-dashboard>=0.8.0.2
Requires-Dist: rq-win; os_name == "nt" or os_name == "win"
Requires-Dist: redis>4.5
Requires-Dist: tldextract
Requires-Dist: pyomo<6.9,>=5.6
Requires-Dist: tabulate
Requires-Dist: timetomodel>=0.7.3
Requires-Dist: timely-beliefs[forecast]>=3.2.1
Requires-Dist: python-dotenv
Requires-Dist: importlib_metadata
Requires-Dist: sqlalchemy>=2.0
Requires-Dist: Flask-SSLify
Requires-Dist: Flask_JSON
Requires-Dist: Flask-Migrate
Requires-Dist: Flask-WTF
Requires-Dist: Flask-Mail
Requires-Dist: Flask-Security-Too[fsqla,mfa]>=5.0
Requires-Dist: Flask-Login
Requires-Dist: Flask-Classful>=0.16
Requires-Dist: Flask-Marshmallow
Requires-Dist: Flask-Cors
Requires-Dist: flask-swagger-ui
Requires-Dist: sentry-sdk[flask]
Requires-Dist: marshmallow>=3
Requires-Dist: marshmallow~=3.0; python_version < "3.11"
Requires-Dist: marshmallow-polyfield
Requires-Dist: marshmallow-sqlalchemy>=0.23.1
Requires-Dist: webargs
Requires-Dist: uniplot>=0.12.1
Requires-Dist: Flask-SQLAlchemy>=2.5.2
Requires-Dist: flask>=1.0
Requires-Dist: werkzeug
Requires-Dist: vl-convert-python
Requires-Dist: Pillow>=10.0.1
Requires-Dist: dictdiffer>=0.9.0
Dynamic: license-file
Dynamic: requires-dist
